{"id": "81d3ce4b-c47a-46f2-87aa-282cf4a6e82a", "status": "FA", "full_name": "Justin Wright-Foreman", "first_name": "Justin", "last_name": "Wright-Foreman", "abbr_name": "J.Wright-Foreman", "height": 72, "weight": 190, "position": "G", "primary_position": "PG", "experience": "1", "college": "Hofstra", "high_school": "Construction (NY)", "birth_place": "Laurelton, NY, USA", "birthdate": "1997-10-27", "updated": "2020-12-09T16:47:02Z", "sr_id": "sr:player:1161222", "rookie_year": 2019, "reference": "1629625", "league": {"id": "4353138d-4c22-4396-95d8-5f587d2df25c", "name": "NBA", "alias": "NBA"}, "draft": {"team_id": "583ece50-fb46-11e1-82cb-f4ce4684ea4c", "year": 2019, "round": "2", "pick": "53"}, "seasons": [{"id": "191e5d0e-ad55-43ef-995c-317ae9ea1213", "year": 2019, "type": "REG", "teams": [{"id": "583ece50-fb46-11e1-82cb-f4ce4684ea4c", "name": "Jazz", "market": "Utah", "alias": "UTA", "sr_id": "sr:team:3434", "reference": "1610612762", "total": {"games_played": 4, "games_started": 0, "minutes": 45.0, "field_goals_made": 7, "field_goals_att": 20, "field_goals_pct": 0.35, "two_points_made": 5, "two_points_att": 10, "two_points_pct": 0.5, "three_points_made": 2, "three_points_att": 10, "three_points_pct": 0.2, "blocked_att": 1, "free_throws_made": 3, "free_throws_att": 4, "free_throws_pct": 0.75, "offensive_rebounds": 0, "defensive_rebounds": 5, "rebounds": 5, "assists": 7, "turnovers": 3, "assists_turnover_ratio": 2.33, "steals": 2, "blocks": 0, "personal_fouls": 5, "tech_fouls": 0, "points": 19, "flagrant_fouls": 0, "ejections": 0, "foulouts": 0, "true_shooting_att": 21.76, "true_shooting_pct": 0.437, "efficiency": 16, "points_off_turnovers": 2, "points_in_paint": 8, "points_in_paint_made": 4, "points_in_paint_att": 7, "points_in_paint_pct": 0.571, "effective_fg_pct": 0.4, "double_doubles": 0, "triple_doubles": 0, "fouls_drawn": 2, "offensive_fouls": 0, "fast_break_pts": 3, "fast_break_att": 1, "fast_break_made": 1, "fast_break_pct": 1.0, "coach_ejections": 0, "second_chance_pct": 0.0, "second_chance_pts": 0, "second_chance_att": 3, "second_chance_made": 0, "minus": 115, "plus": 85, "coach_tech_fouls": 0}, "average": {"minutes": 11.3, "points": 4.8, "off_rebounds": 0.0, "def_rebounds": 1.25, "rebounds": 1.25, "assists": 1.8, "steals": 0.5, "blocks": 0.0, "turnovers": 0.75, "personal_fouls": 1.25, "flagrant_fouls": 0.0, "blocked_att": 0.25, "field_goals_made": 1.75, "field_goals_att": 5.0, "three_points_made": 0.5, "three_points_att": 2.5, "free_throws_made": 0.75, "free_throws_att": 1.0, "two_points_made": 1.25, "two_points_att": 2.5, "efficiency": 4.0, "true_shooting_att": 5.44, "points_off_turnovers": 0.5, "points_in_paint_made": 1.0, "points_in_paint_att": 1.75, "points_in_paint": 2.0, "fouls_drawn": 0.5, "offensive_fouls": 0.0, "fast_break_pts": 0.75, "fast_break_att": 0.25, "fast_break_made": 0.25, "second_chance_pts": 0.0, "second_chance_att": 0.75, "second_chance_made": 0.0}}]}]}