{"id": "3c09ef8a-a6f2-4500-9599-ca7bc8d54300", "status": "ACT", "full_name": "Brad Wanamaker", "first_name": "Brad", "last_name": "Wanamaker", "abbr_name": "B.Wanamaker", "height": 75, "weight": 210, "position": "G", "primary_position": "PG", "jersey_number": "9", "experience": "2", "college": "Pittsburgh", "high_school": "Roman Catholic (PA)", "birth_place": "Philadelphia, PA, USA", "birthdate": "1989-07-25", "updated": "2021-03-26T21:58:24Z", "sr_id": "sr:player:921122", "rookie_year": 2018, "reference": "202954", "league": {"id": "4353138d-4c22-4396-95d8-5f587d2df25c", "name": "NBA", "alias": "NBA"}, "team": {"id": "583ec97e-fb46-11e1-82cb-f4ce4684ea4c", "name": "Hornets", "market": "Charlotte", "alias": "CHA", "sr_id": "sr:team:3430", "reference": "1610612766"}, "draft": {"year": 2011}, "seasons": [{"id": "feb33381-9dbf-45b6-82c1-3c50c9a2b5ce", "year": 2020, "type": "REG", "teams": [{"id": "583ec825-fb46-11e1-82cb-f4ce4684ea4c", "name": "Warriors", "market": "Golden State", "alias": "GSW", "sr_id": "sr:team:3428", "reference": "1610612744", "total": {"games_played": 39, "games_started": 0, "minutes": 625.0, "field_goals_made": 61, "field_goals_att": 173, "field_goals_pct": 0.353, "two_points_made": 48, "two_points_att": 112, "two_points_pct": 0.429, "three_points_made": 13, "three_points_att": 61, "three_points_pct": 0.213, "blocked_att": 22, "free_throws_made": 50, "free_throws_att": 56, "free_throws_pct": 0.893, "offensive_rebounds": 8, "defensive_rebounds": 58, "rebounds": 66, "assists": 99, "turnovers": 37, "assists_turnover_ratio": 2.68, "steals": 26, "blocks": 6, "personal_fouls": 55, "tech_fouls": 2, "points": 185, "flagrant_fouls": 0, "ejections": 0, "foulouts": 0, "true_shooting_att": 197.64, "true_shooting_pct": 0.468, "efficiency": 227, "points_off_turnovers": 27, "points_in_paint": 76, "points_in_paint_made": 38, "points_in_paint_att": 85, "points_in_paint_pct": 0.447, "effective_fg_pct": 0.39, "double_doubles": 0, "triple_doubles": 0, "fouls_drawn": 59, "offensive_fouls": 2, "fast_break_pts": 48, "fast_break_att": 29, "fast_break_made": 16, "fast_break_pct": 0.552, "coach_ejections": 0, "second_chance_pct": 0.375, "second_chance_pts": 11, "second_chance_att": 8, "second_chance_made": 3, "minus": 1376, "plus": 1366, "coach_tech_fouls": 0}, "average": {"minutes": 16.0, "points": 4.7, "off_rebounds": 0.21, "def_rebounds": 1.49, "rebounds": 1.69, "assists": 2.5, "steals": 0.67, "blocks": 0.15, "turnovers": 0.95, "personal_fouls": 1.41, "flagrant_fouls": 0.0, "blocked_att": 0.56, "field_goals_made": 1.56, "field_goals_att": 4.44, "three_points_made": 0.33, "three_points_att": 1.56, "free_throws_made": 1.28, "free_throws_att": 1.44, "two_points_made": 1.23, "two_points_att": 2.87, "efficiency": 5.82, "true_shooting_att": 5.07, "points_off_turnovers": 0.69, "points_in_paint_made": 0.97, "points_in_paint_att": 2.18, "points_in_paint": 1.95, "fouls_drawn": 1.51, "offensive_fouls": 0.05, "fast_break_pts": 1.23, "fast_break_att": 0.74, "fast_break_made": 0.41, "second_chance_pts": 0.28, "second_chance_att": 0.21, "second_chance_made": 0.08}}, {"id": "583ec97e-fb46-11e1-82cb-f4ce4684ea4c", "name": "Hornets", "market": "Charlotte", "alias": "CHA", "sr_id": "sr:team:3430", "reference": "1610612766", "total": {"games_played": 22, "games_started": 0, "minutes": 428.0, "field_goals_made": 54, "field_goals_att": 126, "field_goals_pct": 0.429, "two_points_made": 51, "two_points_att": 102, "two_points_pct": 0.5, "three_points_made": 3, "three_points_att": 24, "three_points_pct": 0.125, "blocked_att": 13, "free_throws_made": 40, "free_throws_att": 45, "free_throws_pct": 0.889, "offensive_rebounds": 10, "defensive_rebounds": 29, "rebounds": 39, "assists": 75, "turnovers": 34, "assists_turnover_ratio": 2.21, "steals": 17, "blocks": 5, "personal_fouls": 39, "tech_fouls": 0, "points": 151, "flagrant_fouls": 0, "ejections": 0, "foulouts": 0, "true_shooting_att": 145.8, "true_shooting_pct": 0.518, "efficiency": 176, "points_off_turnovers": 16, "points_in_paint": 92, "points_in_paint_made": 46, "points_in_paint_att": 83, "points_in_paint_pct": 0.554, "effective_fg_pct": 0.44, "double_doubles": 0, "triple_doubles": 0, "fouls_drawn": 33, "offensive_fouls": 4, "fast_break_pts": 19, "fast_break_att": 18, "fast_break_made": 7, "fast_break_pct": 0.389, "coach_ejections": 0, "second_chance_pct": 0.556, "second_chance_pts": 16, "second_chance_att": 9, "second_chance_made": 5, "minus": 986, "plus": 865, "coach_tech_fouls": 0}, "average": {"minutes": 19.5, "points": 6.9, "off_rebounds": 0.45, "def_rebounds": 1.32, "rebounds": 1.77, "assists": 3.4, "steals": 0.77, "blocks": 0.23, "turnovers": 1.55, "personal_fouls": 1.77, "flagrant_fouls": 0.0, "blocked_att": 0.59, "field_goals_made": 2.45, "field_goals_att": 5.73, "three_points_made": 0.14, "three_points_att": 1.09, "free_throws_made": 1.82, "free_throws_att": 2.05, "two_points_made": 2.32, "two_points_att": 4.64, "efficiency": 8.0, "true_shooting_att": 6.63, "points_off_turnovers": 0.73, "points_in_paint_made": 2.09, "points_in_paint_att": 3.77, "points_in_paint": 4.18, "fouls_drawn": 1.5, "offensive_fouls": 0.18, "fast_break_pts": 0.86, "fast_break_att": 0.82, "fast_break_made": 0.32, "second_chance_pts": 0.73, "second_chance_att": 0.41, "second_chance_made": 0.23}}]}, {"id": "191e5d0e-ad55-43ef-995c-317ae9ea1213", "year": 2019, "type": "REG", "teams": [{"id": "583eccfa-fb46-11e1-82cb-f4ce4684ea4c", "name": "Celtics", "market": "Boston", "alias": "BOS", "sr_id": "sr:team:3422", "reference": "1610612738", "total": {"games_played": 71, "games_started": 1, "minutes": 1369.0, "field_goals_made": 162, "field_goals_att": 362, "field_goals_pct": 0.448, "two_points_made": 125, "two_points_att": 260, "two_points_pct": 0.481, "three_points_made": 37, "three_points_att": 102, "three_points_pct": 0.363, "blocked_att": 26, "free_throws_made": 126, "free_throws_att": 136, "free_throws_pct": 0.926, "offensive_rebounds": 22, "defensive_rebounds": 122, "rebounds": 144, "assists": 179, "turnovers": 76, "assists_turnover_ratio": 2.36, "steals": 61, "blocks": 14, "personal_fouls": 133, "tech_fouls": 1, "points": 487, "flagrant_fouls": 0, "ejections": 0, "foulouts": 0, "true_shooting_att": 421.84, "true_shooting_pct": 0.577, "efficiency": 599, "points_off_turnovers": 111, "points_in_paint": 210, "points_in_paint_made": 105, "points_in_paint_att": 208, "points_in_paint_pct": 0.505, "effective_fg_pct": 0.499, "double_doubles": 0, "triple_doubles": 0, "fouls_drawn": 99, "offensive_fouls": 5, "fast_break_pts": 129, "fast_break_att": 77, "fast_break_made": 50, "fast_break_pct": 0.649, "coach_ejections": 0, "second_chance_pct": 0.556, "second_chance_pts": 43, "second_chance_att": 27, "second_chance_made": 15, "minus": 3052, "plus": 3185, "coach_tech_fouls": 0}, "average": {"minutes": 19.3, "points": 6.9, "off_rebounds": 0.31, "def_rebounds": 1.72, "rebounds": 2.03, "assists": 2.5, "steals": 0.86, "blocks": 0.2, "turnovers": 1.07, "personal_fouls": 1.87, "flagrant_fouls": 0.0, "blocked_att": 0.37, "field_goals_made": 2.28, "field_goals_att": 5.1, "three_points_made": 0.52, "three_points_att": 1.44, "free_throws_made": 1.77, "free_throws_att": 1.92, "two_points_made": 1.76, "two_points_att": 3.66, "efficiency": 8.44, "true_shooting_att": 5.94, "points_off_turnovers": 1.56, "points_in_paint_made": 1.48, "points_in_paint_att": 2.93, "points_in_paint": 2.96, "fouls_drawn": 1.39, "offensive_fouls": 0.07, "fast_break_pts": 1.82, "fast_break_att": 1.08, "fast_break_made": 0.7, "second_chance_pts": 0.61, "second_chance_att": 0.38, "second_chance_made": 0.21}}]}, {"id": "47c9979e-5c3f-453d-ac75-734d17412e3f", "year": 2018, "type": "REG", "teams": [{"id": "583eccfa-fb46-11e1-82cb-f4ce4684ea4c", "name": "Celtics", "market": "Boston", "alias": "BOS", "sr_id": "sr:team:3422", "reference": "1610612738", "total": {"games_played": 36, "games_started": 0, "minutes": 343.0, "field_goals_made": 50, "field_goals_att": 105, "field_goals_pct": 0.476, "two_points_made": 34, "two_points_att": 66, "two_points_pct": 0.515, "three_points_made": 16, "three_points_att": 39, "three_points_pct": 0.41, "blocked_att": 2, "free_throws_made": 24, "free_throws_att": 28, "free_throws_pct": 0.857, "offensive_rebounds": 3, "defensive_rebounds": 38, "rebounds": 41, "assists": 56, "turnovers": 19, "assists_turnover_ratio": 2.95, "steals": 12, "blocks": 2, "personal_fouls": 34, "tech_fouls": 0, "points": 140, "flagrant_fouls": 0, "ejections": 0, "foulouts": 1, "true_shooting_att": 117.32, "true_shooting_pct": 0.597, "efficiency": 173, "points_off_turnovers": 28, "points_in_paint": 50, "points_in_paint_made": 25, "points_in_paint_att": 44, "points_in_paint_pct": 0.568, "effective_fg_pct": 0.552, "double_doubles": 0, "triple_doubles": 0, "fouls_drawn": 23, "offensive_fouls": 1, "fast_break_pts": 45, "fast_break_att": 23, "fast_break_made": 18, "fast_break_pct": 0.783, "coach_ejections": 0, "second_chance_pct": 0.667, "second_chance_pts": 10, "second_chance_att": 6, "second_chance_made": 4, "minus": 715, "plus": 787, "coach_tech_fouls": 0}, "average": {"minutes": 9.5, "points": 3.9, "off_rebounds": 0.08, "def_rebounds": 1.06, "rebounds": 1.14, "assists": 1.6, "steals": 0.33, "blocks": 0.06, "turnovers": 0.53, "personal_fouls": 0.94, "flagrant_fouls": 0.0, "blocked_att": 0.06, "field_goals_made": 1.39, "field_goals_att": 2.92, "three_points_made": 0.44, "three_points_att": 1.08, "free_throws_made": 0.67, "free_throws_att": 0.78, "two_points_made": 0.94, "two_points_att": 1.83, "efficiency": 4.81, "true_shooting_att": 3.26, "points_off_turnovers": 0.78, "points_in_paint_made": 0.69, "points_in_paint_att": 1.22, "points_in_paint": 1.39, "fouls_drawn": 0.64, "offensive_fouls": 0.03, "fast_break_pts": 1.25, "fast_break_att": 0.64, "fast_break_made": 0.5, "second_chance_pts": 0.28, "second_chance_att": 0.17, "second_chance_made": 0.11}}]}]}