{"id": "27c98767-f7ec-4dfa-96db-8b9ff605d2ff", "status": "FA", "full_name": "Vince Hunter", "first_name": "Vincent", "last_name": "Hunter", "abbr_name": "V.Hunter", "height": 80, "weight": 208, "position": "F", "primary_position": "PF", "experience": "0", "college": "UTEP", "high_school": "Consortium Prep", "birth_place": "Detroit, MI, USA", "birthdate": "1994-08-05", "updated": "2019-08-29T15:45:52Z", "rookie_year": 2017, "reference": "1626205", "league": {"id": "4353138d-4c22-4396-95d8-5f587d2df25c", "name": "NBA", "alias": "NBA"}, "seasons": [{"id": "7dcb5184-ab33-49fe-bd18-c4ca2b1cfc08", "year": 2017, "type": "REG", "teams": [{"id": "583eca88-fb46-11e1-82cb-f4ce4684ea4c", "name": "Grizzlies", "market": "Memphis", "alias": "MEM", "sr_id": "sr:team:3415", "reference": "1610612763", "total": {"games_played": 4, "games_started": 0, "minutes": 7.0, "field_goals_made": 3, "field_goals_att": 5, "field_goals_pct": 0.6, "two_points_made": 3, "two_points_att": 5, "two_points_pct": 0.6, "three_points_made": 0, "three_points_att": 0, "three_points_pct": 0.0, "blocked_att": 0, "free_throws_made": 0, "free_throws_att": 0, "free_throws_pct": 0.0, "offensive_rebounds": 2, "defensive_rebounds": 1, "rebounds": 3, "assists": 0, "turnovers": 1, "assists_turnover_ratio": 0.0, "steals": 0, "blocks": 1, "personal_fouls": 0, "tech_fouls": 0, "points": 6, "flagrant_fouls": 0, "ejections": 0, "foulouts": 0, "true_shooting_att": 5.0, "true_shooting_pct": 0.6, "efficiency": 7, "points_off_turnovers": 0, "points_in_paint": 4, "points_in_paint_made": 2, "points_in_paint_att": 4, "points_in_paint_pct": 0.5, "effective_fg_pct": 0.6, "double_doubles": 0, "triple_doubles": 0, "fouls_drawn": 0, "offensive_fouls": 0, "fast_break_pts": 0, "fast_break_att": 0, "fast_break_made": 0, "fast_break_pct": 0.0, "coach_ejections": 0, "second_chance_pct": 0.5, "second_chance_pts": 2, "second_chance_att": 2, "second_chance_made": 1, "minus": 12, "plus": 18, "coach_tech_fouls": 0}, "average": {"minutes": 1.8, "points": 1.5, "off_rebounds": 0.5, "def_rebounds": 0.25, "rebounds": 0.75, "assists": 0.0, "steals": 0.0, "blocks": 0.25, "turnovers": 0.25, "personal_fouls": 0.0, "flagrant_fouls": 0.0, "blocked_att": 0.0, "field_goals_made": 0.75, "field_goals_att": 1.25, "three_points_made": 0.0, "three_points_att": 0.0, "free_throws_made": 0.0, "free_throws_att": 0.0, "two_points_made": 0.75, "two_points_att": 1.25, "efficiency": 1.75, "true_shooting_att": 1.25, "points_off_turnovers": 0.0, "points_in_paint_made": 0.5, "points_in_paint_att": 1.0, "points_in_paint": 1.0, "fouls_drawn": 0.0, "offensive_fouls": 0.0, "fast_break_pts": 0.0, "fast_break_att": 0.0, "fast_break_made": 0.0, "second_chance_pts": 0.5, "second_chance_att": 0.5, "second_chance_made": 0.25}}]}]}